MANIFEST.in
README.md
pyproject.toml
requirements.txt
setup.py
amuse_ekster.egg-info/PKG-INFO
amuse_ekster.egg-info/SOURCES.txt
amuse_ekster.egg-info/dependency_links.txt
amuse_ekster.egg-info/requires.txt
amuse_ekster.egg-info/top_level.txt
bin/ekster.py
src/amuse/ext/ekster/__init__.py
src/amuse/ext/ekster/_version.py
src/amuse/ext/ekster/available_codes.py
src/amuse/ext/ekster/basic_class.py
src/amuse/ext/ekster/bridge.py
src/amuse/ext/ekster/cooling_class.py
src/amuse/ext/ekster/diagnostics.py
src/amuse/ext/ekster/ekster_settings.py
src/amuse/ext/ekster/feedback_class.py
src/amuse/ext/ekster/find_clusters.py
src/amuse/ext/ekster/gas_class.py
src/amuse/ext/ekster/interface.py
src/amuse/ext/ekster/merge_recipes.py
src/amuse/ext/ekster/plotting_class.py
src/amuse/ext/ekster/read_settings.py
src/amuse/ext/ekster/res_increase.py
src/amuse/ext/ekster/run.py
src/amuse/ext/ekster/setup_codes.py
src/amuse/ext/ekster/sinks_class.py
src/amuse/ext/ekster/spiral_potential.py
src/amuse/ext/ekster/star_forming_region_class.py
src/amuse/ext/ekster/stellar_dynamics_class.py
src/amuse/ext/ekster/stellar_evolution_class.py
src/amuse/ext/ekster/stellar_interactions.py
src/amuse/ext/ekster/stellar_wind_class.py